pyschemagen/__init__.py
pyschemagen/element_types.py
pyschemagen/parser.py
pyschemagen-0.0.4.dist-info/LICENSE
pyschemagen-0.0.4.dist-info/METADATA
pyschemagen-0.0.4.dist-info/WHEEL
pyschemagen-0.0.4.dist-info/top_level.txt
pyschemagen-0.0.4.dist-info/RECORD
