Metadata-Version: 2.1
Name: pyschemagen
Version: 0.0.4
Summary: A package to generate orator DB schemas from a python dict.
Home-page: https://github.com/alexwhb/PySchemaGen
Author: alexwhb
License: Apache 2.0
Platform: UNKNOWN
Classifier: Programming Language :: Python :: 3
Classifier: Operating System :: OS Independent
Requires-Python: >=3.4
Requires-Dist: orator
